thraxilsettings/__init__.py
thraxilsettings/__init__.pyc
thraxilsettings/compose.py
thraxilsettings/docker.py
thraxilsettings/production.py
thraxilsettings/shared.py
thraxilsettings/shared.pyc
thraxilsettings/test2.pyc
thraxilsettings-4.0.1.dist-info/METADATA
thraxilsettings-4.0.1.dist-info/WHEEL
thraxilsettings-4.0.1.dist-info/top_level.txt
thraxilsettings-4.0.1.dist-info/RECORD
