Metadata-Version: 2.1
Name: thraxilsettings
Version: 4.0.1
Summary: My common base settings
Home-page: https://github.com/thraxil/thraxilsettings
Author: Anders Pearson
Author-email: anders@columbia.edu
License: BSD
Platform: any
Requires-Dist: boto3
Requires-Dist: django-debug-toolbar
Requires-Dist: django-jenkins
Requires-Dist: django-markwhat
Requires-Dist: django-smoketest
Requires-Dist: django-storages
Requires-Dist: django-waffle
Requires-Dist: django-compressor
Requires-Dist: gunicorn
Requires-Dist: raven
